salesforce_mcp_plugin/__init__.py
salesforce_mcp_plugin/__main__.py
salesforce_mcp_plugin/main.py
salesforce_mcp_plugin/salesforce.py
salesforce_mcp_plugin-0.3.4.dist-info/METADATA
salesforce_mcp_plugin-0.3.4.dist-info/WHEEL
salesforce_mcp_plugin-0.3.4.dist-info/entry_points.txt
salesforce_mcp_plugin-0.3.4.dist-info/top_level.txt
salesforce_mcp_plugin-0.3.4.dist-info/RECORD
