Metadata-Version: 2.4
Name: salesforce_mcp_plugin
Version: 0.3.4
Summary: An MCP tool to query Salesforce Account data by customer name
Author-email: Mary <545536626@qq.com>
Requires-Python: >=3.8
Requires-Dist: httpx>=0.24.0
Requires-Dist: requests>=2.31.0
Requires-Dist: mcp[cli]>=1.9.1
